feature_engine/VERSION
feature_engine/__init__.py
feature_engine/dataframe_checks.py
feature_engine/py.typed
feature_engine/tags.py
feature_engine-1.9.1.dist-info/licenses/LICENSE.md
feature_engine-1.9.1.dist-info/METADATA
feature_engine-1.9.1.dist-info/WHEEL
feature_engine-1.9.1.dist-info/top_level.txt
feature_engine-1.9.1.dist-info/RECORD
