Metadata-Version: 2.4
Name: feature_engine
Version: 1.9.1
Summary: Feature engineering and selection package with Scikit-learn's fit transform functionality
Author-email: Soledad Galli <solegalli@protonmail.com>
License: BSD 3 clause
Project-URL: Homepage, http://github.com/feature-engine/feature_engine
Classifier: License :: OSI Approved :: BSD License
Classifier: Programming Language :: Python :: 3.9
Classifier: Programming Language :: Python :: 3.10
Classifier: Programming Language :: Python :: 3.11
Classifier: Programming Language :: Python :: 3.12
Classifier: Programming Language :: Python :: 3.13
Requires-Python: >=3.9.0
License-File: LICENSE.md
Requires-Dist: numpy>=1.18.2
Requires-Dist: pandas>=2.2.0
Requires-Dist: scikit-learn>=1.4.0
Requires-Dist: scipy>=1.4.1
Requires-Dist: statsmodels>=0.11.1
Provides-Extra: docs
Requires-Dist: docutils==0.16; extra == "docs"
Requires-Dist: Sphinx>=4.3.2; extra == "docs"
Requires-Dist: pydata_sphinx_theme>=0.7.2; extra == "docs"
Requires-Dist: sphinx_autodoc_typehints<=1.21.3,>=1.11.1; extra == "docs"
Requires-Dist: numpydoc>=0.9.2; extra == "docs"
Provides-Extra: tests
Requires-Dist: pytest>=5.4.1; extra == "tests"
Requires-Dist: black>=21.5b1; extra == "tests"
Requires-Dist: coverage>=6.4.4; extra == "tests"
Requires-Dist: flake8>=3.9.2; extra == "tests"
Requires-Dist: isort>=5.8.0; extra == "tests"
Requires-Dist: mypy>=0.740; extra == "tests"
Dynamic: license-file
